[
  {
    "_id": "59ca383c3e2fca6f4f1e9a14",
    "index": 0,
    "guid": "83d09d15-aa50-4c64-bef7-930bf46bbdf6",
    "isActive": true,
    "balance": "$3,678.40",
    "picture": "http://placehold.it/32x32",
    "age": 34,
    "eyeColoreyeColoreyeColoreyeColor": "brown",
    "name": "Heath Gaines",
    "gender": "male",
    "company": "NETUR",
    "email": "heathgaines@netur.com",
    "phone": "+1 (937) 500-3890",
    "address": "231 Minna Street, Coalmont, South Carolina, 2101",
    "about": "Culpa ullamco aute nulla enim deserunt nostrud culpa dolor sunt minim. Ut velit cillum cupidatat eu duis deserunt qui adipisicing occaecat. Aliquip in excepteur eiusmod in adipisicing. Magna eu id proident cupidatat labore cupidatat ad mollit irure do irure duis aliquip.\r\n",
    "registered": "2015-09-28T05:00:56 -06:-30",
    "latitude": -53.74095,
    "longitude": 105.870955
  }
]